howde/__init__.py
howde/config.py
howde/core.py
howde/pipeline.py
howde/utils.py
howde-1.1.dist-info/licenses/LICENSE.txt
howde-1.1.dist-info/METADATA
howde-1.1.dist-info/WHEEL
howde-1.1.dist-info/top_level.txt
howde-1.1.dist-info/RECORD
