Metadata-Version: 2.4
Name: HoWDe
Version: 1.1
Summary: A package for detecting home and work locations from timestamped stop locations.
Home-page: https://github.com/LLucchini/HoWDe
Author: Silvia De Sojo Caso, Lorenzo Lucchini, Laura Alessandretti
Author-email: Lorenzo Lucchini <lorenzo.f.lucchini.work@gmail.com>, Silvia De Sojo Caso <sdesojoc@gmail.com>
License: MIT License
Project-URL: Homepage, https://github.com/LLucchini/HoWDe
Project-URL: Repository, https://github.com/LLucchini/HoWDe
Project-URL: Documentation, https://github.com/LLucchini/HoWDe/blob/main/README.md
Project-URL: Tutorials, https://github.com/LLucchini/HoWDe/tree/main/tutorials
Classifier: Programming Language :: Python :: 3
Classifier: License :: OSI Approved :: MIT License
Classifier: Operating System :: OS Independent
Requires-Python: >=3.6
License-File: LICENSE.txt
Requires-Dist: numpy
Requires-Dist: pandas
Requires-Dist: python-dateutil
Requires-Dist: tqdm
Requires-Dist: pyspark
Dynamic: author
Dynamic: home-page
Dynamic: license-file
Dynamic: requires-python
